<?xml version="1.0" encoding="UTF-8"?>
<PropertyList>
	<logic>
		<name>Gear retracted indicator light illumination</name>
		<input>
			<and>
				<or>
					<and>
						<equals>
							<property>/gear/gear[0]/position-norm</property>
							<value>0</value>
						</equals>
						<equals>
							<property>/gear/gear[1]/position-norm</property>
							<value>0</value>
						</equals>
						<equals>
							<property>/gear/gear[2]/position-norm</property>
							<value>0</value>
						</equals>
					</and>
					<property>/sim/model/controls/gear/retracted-lamp-test</property>
				</or>
				<property>/sim/model/controls/gear/powered</property>
			</and>
		</input>
		<output>/sim/model/controls/gear/retracted-lamp-illumination</output>
	</logic>
	
	<logic>
		<name>Gear extended indicator light illumination</name>
		<input>
			<and>
				<or>
					<and>
						<equals>
							<property>/gear/gear[0]/position-norm</property>
							<value>1</value>
						</equals>
						<equals>
							<property>/gear/gear[1]/position-norm</property>
							<value>1</value>
						</equals>
						<equals>
							<property>/gear/gear[2]/position-norm</property>
							<value>1</value>
						</equals>
					</and>
					<equals>
						<property>/sim/model/controls/gear/extended-lamp-test</property>
						<value>2</value> <!-- position 1 (half pushed) is warning sound test, only position 2 (fully in) is light test -->
					</equals>
				</or>
				<property>/sim/model/controls/gear/powered</property>
			</and>
			<value>1</value>
		</input>
		<output>/sim/model/controls/gear/extended-lamp-illumination</output>
	</logic>
	<filter>
		<type>noise-spike</type>
		<max-rate-of-change>1</max-rate-of-change>
		<input>/controls/gear/gear-down</input>
		<output>/sim/model/controls/gear-lever-norm</output>
	</filter>
	
	<filter>
		<type>noise-spike</type>
		<max-rate-of-change>1</max-rate-of-change>
		<input>/controls/gear/brake-parking</input>
		<output>/sim/model/controls/parking-brake-lever-norm</output>
	</filter>
	<filter>
		<type>noise-spike</type>
		<max-rate-of-change>1</max-rate-of-change>
		<input>/controls/flight/flaps</input>
		<output>/sim/model/controls/flaps-lever-norm</output>
	</filter>
</PropertyList>
